KDHexcel/KDHcalc.py
KDHexcel/KDHcalcTest.py
KDHexcel/KDHexcel.py
KDHexcel/KDHexcelTest.py
KDHexcel/__init__.py
KDHexcel/data/jemu.csv
KDHexcel-0.0.1.4.dist-info/METADATA
KDHexcel-0.0.1.4.dist-info/WHEEL
KDHexcel-0.0.1.4.dist-info/top_level.txt
KDHexcel-0.0.1.4.dist-info/RECORD
