Metadata-Version: 2.1
Name: KDHexcel
Version: 0.0.1.4
Summary: 엑셀생성
Home-page: https://github.com/KimDaeHo26/python
Author: 김대호
Author-email: jmee2626@gmail.com
License: MIT
Platform: UNKNOWN
Requires-Python: >=3
